adv_data_mapper/__init__.py
adv_data_mapper-0.0.1.dist-info/METADATA
adv_data_mapper-0.0.1.dist-info/WHEEL
adv_data_mapper-0.0.1.dist-info/top_level.txt
adv_data_mapper-0.0.1.dist-info/RECORD
