Metadata-Version: 2.4
Name: adv-data-mapper
Version: 0.0.1
Summary: Advanced Data Mapper: A library for transforming data between different formats
Home-page: https://github.com/TrentDevStuff/data-mapper-module
Author: AdvancedMD
Author-email: your-email@example.com
Classifier: Programming Language :: Python :: 3
Classifier: License :: OSI Approved :: MIT License
Classifier: Operating System :: OS Independent
Requires-Python: >=3.6
Dynamic: author
Dynamic: author-email
Dynamic: classifier
Dynamic: description
Dynamic: description-content-type
Dynamic: home-page
Dynamic: requires-python
Dynamic: summary
